{
 "topic": "50. Ч. 7. Площадь",
 "audio_url": "https://raw.githubusercontent.com/eduardgagite/nosu-task/main/raw/50.%20%D0%A7.%207.%20%D0%9F%D0%BB%D0%BE%D1%89%D0%B0%D0%B4%D1%8C.mp3",
 "phrases": [
  {
   "i": 1,
   "oset": "Горӕты сӕйраг фӕзы ном куыд у?",
   "rus": "Как называется центральная площадь города?",
   "start": 10.42,
   "end": 12.56,
   "flag": "-"
  },
  {
   "i": 2,
   "oset": "Ацы фӕзы ном куыд у?",
   "rus": "Как эта площадь называется?",
   "start": 12.56,
   "end": 12.92,
   "flag": "-"
  },
  {
   "i": 3,
   "oset": "Ленины фӕзмӕ-ма мӕ схӕццӕ кӕн.",
   "rus": "Проводи меня до площади Ленина.",
   "start": 21.51,
   "end": 29.15,
   "flag": "-"
  }
 ]
}