{
 "topic": "65. Ч.24. Курсы",
 "audio_url": "https://raw.githubusercontent.com/eduardgagite/nosu-task/main/raw/65.%20%D0%A7.24.%20%D0%9A%D1%83%D1%80%D1%81%D1%8B.mp3",
 "phrases": [
  {
   "i": 1,
   "oset": "Уӕ институты экзаментӕм цӕттӕгӕнӕн курсытӕ ис?",
   "rus": "Есть ли при вашем институте подготовительные курсы?",
   "start": 0.0,
   "end": 0.0,
   "flag": "нет осетинского аудио — проверить"
  },
  {
   "i": 2,
   "oset": "Ӕз ахуыр кӕнын…",
   "rus": "Я учусь…",
   "start": 12.04,
   "end": 43.09,
   "flag": "-"
  },
  {
   "i": 3,
   "oset": "офисты кусджытӕ цӕттӕгӕнӕн курсыты.",
   "rus": "на курсах по подготовке офисных работников.",
   "start": 52.26,
   "end": 55.28,
   "flag": "-"
  },
  {
   "i": 4,
   "oset": "персоналон компьютерты оператортӕ цӕттӕгӕнӕн курсыты.",
   "rus": "на курсах по подготовке операторов персональных компьютеров.",
   "start": 56.0,
   "end": 61.06,
   "flag": "-"
  }
 ]
}